tzager/__init__.py
tzager/adverse_effects.py
tzager/anatomies.py
tzager/attention.py
tzager/bayesian.py
tzager/brainstorm.py
tzager/causative_agents.py
tzager/diseases.py
tzager/fractals.py
tzager/general_goal.py
tzager/get_connections.py
tzager/hbn.py
tzager/input_abstracts.py
tzager/input_papers.py
tzager/knowledge_modeling.py
tzager/literature.py
tzager/organisms.py
tzager/pdf_paper.py
tzager/phenomena.py
tzager/pmids_filters.py
tzager/predictors.py
tzager/readData.py
tzager/symptoms.py
tzager/therapeutic_agents.py
tzager/train.py
tzager/tzagerBayesian.py
tzager/visualize.py
tzager/why.py
tzager/data/bayesian_network_sm1
tzager/data/bayesian_network_sm2
tzager-1.0.5.1.5.dist-info/LICENSE
tzager-1.0.5.1.5.dist-info/METADATA
tzager-1.0.5.1.5.dist-info/WHEEL
tzager-1.0.5.1.5.dist-info/top_level.txt
tzager-1.0.5.1.5.dist-info/RECORD
