Metadata-Version: 2.1
Name: tzager
Version: 1.0.5.1.5
Summary: A demo example package
Home-page: https://github.com/tzagerAI/tzager
Author: tzager
Author-email: nikos@intoolab.com,a.ntokos@intoolab.com
License: UNKNOWN
Project-URL: Code, https://github.com/tzagerAI/tzager
Platform: UNKNOWN
Classifier: Programming Language :: Python :: 3
Classifier: License :: OSI Approved :: MIT License
Classifier: Operating System :: OS Independent
Requires-Python: >=3.6
Requires-Dist: requests
Requires-Dist: pdfminer
Requires-Dist: pandas
Requires-Dist: networkx
Requires-Dist: matplotlib
Requires-Dist: tqdm
